xiaohongshu_ecommerce-0.1.0.dist-info/METADATA
xiaohongshu_ecommerce-0.1.0.dist-info/WHEEL
xiaohongshu_ecommerce-0.1.0.dist-info/entry_points.txt
xiaohongshu_ecommerce-0.1.0.dist-info/licenses/LICENSE
xiaohongshu_ecommerce/__init__.py
xiaohongshu_ecommerce/client/__init__.py
xiaohongshu_ecommerce/client/after_sale.py
xiaohongshu_ecommerce/client/base.py
xiaohongshu_ecommerce/client/boutique.py
xiaohongshu_ecommerce/client/common.py
xiaohongshu_ecommerce/client/data.py
xiaohongshu_ecommerce/client/delivery_voucher.py
xiaohongshu_ecommerce/client/express.py
xiaohongshu_ecommerce/client/finance.py
xiaohongshu_ecommerce/client/instant_shopping.py
xiaohongshu_ecommerce/client/inventory.py
xiaohongshu_ecommerce/client/invoice.py
xiaohongshu_ecommerce/client/material.py
xiaohongshu_ecommerce/client/oauth.py
xiaohongshu_ecommerce/client/order.py
xiaohongshu_ecommerce/client/package.py
xiaohongshu_ecommerce/client/product.py
xiaohongshu_ecommerce/config.py
xiaohongshu_ecommerce/errors.py
xiaohongshu_ecommerce/http.py
xiaohongshu_ecommerce/models/__init__.py
xiaohongshu_ecommerce/models/after_sale.py
xiaohongshu_ecommerce/models/base.py
xiaohongshu_ecommerce/models/boutique.py
xiaohongshu_ecommerce/models/common.py
xiaohongshu_ecommerce/models/data.py
xiaohongshu_ecommerce/models/delivery_voucher.py
xiaohongshu_ecommerce/models/express.py
xiaohongshu_ecommerce/models/finance.py
xiaohongshu_ecommerce/models/instant_shopping.py
xiaohongshu_ecommerce/models/inventory.py
xiaohongshu_ecommerce/models/invoice.py
xiaohongshu_ecommerce/models/material.py
xiaohongshu_ecommerce/models/oauth.py
xiaohongshu_ecommerce/models/order.py
xiaohongshu_ecommerce/models/package.py
xiaohongshu_ecommerce/models/pagination.py
xiaohongshu_ecommerce/models/product.py
xiaohongshu_ecommerce/signing.py
xiaohongshu_ecommerce/token_manager.py
xiaohongshu_ecommerce/utils/__init__.py
xiaohongshu_ecommerce/utils/datetime.py
xiaohongshu_ecommerce/utils/serialization.py
xiaohongshu_ecommerce-0.1.0.dist-info/RECORD
