Metadata-Version: 2.1
Name: xiaohongshu-ecommerce
Version: 0.1.0
Summary: Python SDK for Xiaohongshu (Little Red Book) ecommerce API with automatic token management
Author-Email: andersonby <andersonby@163.com>
License: MIT
Requires-Python: >=3.12
Requires-Dist: httpx>=0.28.1
